transformation_func/__init__.py
transformation_func/main.py
transformation_func-0.1.0.dist-info/METADATA
transformation_func-0.1.0.dist-info/WHEEL
transformation_func-0.1.0.dist-info/RECORD
