Metadata-Version: 2.1
Name: transformation-func
Version: 0.1.0
Summary: 
Author: Julia Gunevic
Author-email: julia.gunevic@gmail.com
Requires-Python: >=3.12,<4.0
Classifier: Programming Language :: Python :: 3
Classifier: Programming Language :: Python :: 3.12
Requires-Dist: obspy (>=1.4.1,<2.0.0)
Requires-Dist: scipy (>=1.13.1,<2.0.0)
